Metadata-Version: 2.1
Name: os-translator
Version: 1.3
Summary: Run this module to translate a string to a given language using Google Translate API.
Home-page: https://github.com/osfunapps/os-translator-py
Author: Oz Shabat
Author-email: admin@os-apps.com
License: MIT
Keywords: python,osfunapps,osapps,Google Translate,api
Platform: UNKNOWN
Classifier: Development Status :: 5 - Production/Stable
Classifier: Intended Audience :: Developers
Classifier: Topic :: Software Development :: Build Tools
Classifier: License :: OSI Approved :: MIT License
Classifier: Programming Language :: Python :: 3
Classifier: Programming Language :: Python :: 3.4
Classifier: Programming Language :: Python :: 3.5
Classifier: Programming Language :: Python :: 3.6
Classifier: Programming Language :: Python :: 3.9
License-File: LICENSE.txt
